mysqlpulse/__init__.py
mysqlpulse/mysqlpulse.py
mysqlpulse-1.0.0.dist-info/licenses/LICENSE
mysqlpulse-1.0.0.dist-info/METADATA
mysqlpulse-1.0.0.dist-info/WHEEL
mysqlpulse-1.0.0.dist-info/top_level.txt
mysqlpulse-1.0.0.dist-info/RECORD
