Metadata-Version: 2.4
Name: mysqlpulse
Version: 1.0.0
Summary: A high-performance MySQL database helper with connection pooling and query caching; 支持连接池和查询缓存的高性能MySQL数据库操作工具
Home-page: https://github.com/cxfjh/mysqlhelper
Author: cxfjh
Author-email: 2449579731@qq.com
Keywords: mysql,database,helper,connection pool,query caching,MySQL,数据库,助手,连接池,查询缓存
Classifier: Programming Language :: Python :: 3
Classifier: License :: OSI Approved :: MIT License
Classifier: Operating System :: OS Independent
Classifier: Topic :: Database
Classifier: Topic :: Software Development :: Libraries
Requires-Python: >=3.7
License-File: LICENSE
Requires-Dist: mysqlclient>=2.1.1
Requires-Dist: dbutils>=2.0
Dynamic: author
Dynamic: author-email
Dynamic: classifier
Dynamic: description
Dynamic: description-content-type
Dynamic: home-page
Dynamic: keywords
Dynamic: license-file
Dynamic: requires-dist
Dynamic: requires-python
Dynamic: summary
